fridom/__init__.py
fridom/framework/__init__.py
fridom/framework/clock.py
fridom/framework/configuration.py
fridom/framework/exceptions.py
fridom/framework/field_variable.py
fridom/framework/logger.py
fridom/framework/model.py
fridom/framework/model_settings_base.py
fridom/framework/model_state.py
fridom/framework/state_base.py
fridom/framework/timing_module.py
fridom/framework/domain_decomposition/__init__.py
fridom/framework/domain_decomposition/domain_decomposition.py
fridom/framework/domain_decomposition/jax_decomposition.py
fridom/framework/domain_decomposition/single_decomposition.py
fridom/framework/domain_decomposition/mpi_decomposition/__init__.py
fridom/framework/domain_decomposition/mpi_decomposition/domain_decomposition.py
fridom/framework/domain_decomposition/mpi_decomposition/parallel_fft.py
fridom/framework/domain_decomposition/mpi_decomposition/subdomain.py
fridom/framework/domain_decomposition/mpi_decomposition/transformer.py
fridom/framework/grid/__init__.py
fridom/framework/grid/boundary_type.py
fridom/framework/grid/diff_module.py
fridom/framework/grid/dummy_interpolation.py
fridom/framework/grid/fft_padding.py
fridom/framework/grid/grid_base.py
fridom/framework/grid/interpolation_module.py
fridom/framework/grid/position.py
fridom/framework/grid/water_mask.py
fridom/framework/grid/cartesian/__init__.py
fridom/framework/grid/cartesian/discrete_spectral_operators.py
fridom/framework/grid/cartesian/fft.py
fridom/framework/grid/cartesian/finite_differences.py
fridom/framework/grid/cartesian/grid.py
fridom/framework/grid/cartesian/linear_interpolation.py
fridom/framework/grid/cartesian/polynomial_interpolation.py
fridom/framework/grid/cartesian/spectral_diff.py
fridom/framework/grid/spectral/__init__.py
fridom/framework/grid/spectral/grid.py
fridom/framework/modules/__init__.py
fridom/framework/modules/figure_saver.py
fridom/framework/modules/module.py
fridom/framework/modules/module_container.py
fridom/framework/modules/netcdf_writer.py
fridom-0.0.5.dist-info/LICENSE
fridom-0.0.5.dist-info/METADATA
fridom-0.0.5.dist-info/WHEEL
fridom-0.0.5.dist-info/top_level.txt
fridom-0.0.5.dist-info/RECORD
