Metadata-Version: 2.2
Name: fridom
Version: 0.0.5
Summary: Framework for Idealized Ocean Models
Author-email: Silvano Rosenau <silvano.rosenau@uni-hamburg.de>
License: MIT License
Project-URL: Repository, https://github.com/Gordi42/FRIDOM
Keywords: oceanography,idealized ocean models,modeling,numerical modeling
Classifier: Programming Language :: Python :: 3
Classifier: License :: OSI Approved :: MIT License
Classifier: Operating System :: OS Independent
Classifier: Development Status :: 2 - Pre-Alpha
Requires-Python: >=3.8
License-File: LICENSE
Requires-Dist: lazypimp
Requires-Dist: numpy
Requires-Dist: scipy
Requires-Dist: netCDF4
Requires-Dist: tqdm
Requires-Dist: dill
Requires-Dist: IPython
Requires-Dist: coloredlogs
Requires-Dist: regex
Provides-Extra: cupy
Requires-Dist: cupy; extra == "cupy"
Provides-Extra: jax
Requires-Dist: jax; extra == "jax"
Provides-Extra: jax-cuda
Requires-Dist: jax[cuda12]; extra == "jax-cuda"
Provides-Extra: dev
Requires-Dist: jax[cuda12]; extra == "dev"
Requires-Dist: cupy-cuda12x; extra == "dev"
Requires-Dist: pylint; extra == "dev"
Requires-Dist: pytest; extra == "dev"
Requires-Dist: coverage; extra == "dev"
Requires-Dist: xarray; extra == "dev"
Requires-Dist: matplotlib; extra == "dev"
Requires-Dist: imageio[ffmpeg]; extra == "dev"
Requires-Dist: ipykernel; extra == "dev"
